fn_validator.py
setup.py
fn_arg_validator.egg-info/PKG-INFO
fn_arg_validator.egg-info/SOURCES.txt
fn_arg_validator.egg-info/dependency_links.txt
fn_arg_validator.egg-info/pbr.json
fn_arg_validator.egg-info/top_level.txt