Metadata-Version: 1.0
Name: fn-arg-validator
Version: 0.12
Summary: Provides a decorates which validates the arguments passed to a function
Home-page: UNKNOWN
Author: aash
Author-email: aash.discover@gmail.com
License: UNKNOWN
Platform: UNKNOWN
